ckanext/__init__.py
ckanext/recaptcha/__init__.py
ckanext/recaptcha/config.py
ckanext/recaptcha/plugin.py
ckanext/recaptcha/assets/recaptcha-v2.js
ckanext/recaptcha/assets/recaptcha-v3.js
ckanext/recaptcha/assets/webassets.yml
ckanext/recaptcha/templates/page.html
ckanext/recaptcha/tests/__init__.py
ckanext/recaptcha/tests/test_plugin.py
ckanext_recaptcha-0.1.0.post1.dist-info/LICENSE
ckanext_recaptcha-0.1.0.post1.dist-info/METADATA
ckanext_recaptcha-0.1.0.post1.dist-info/WHEEL
ckanext_recaptcha-0.1.0.post1.dist-info/entry_points.txt
ckanext_recaptcha-0.1.0.post1.dist-info/top_level.txt
ckanext_recaptcha-0.1.0.post1.dist-info/RECORD
